[{"first_name":"Sleiman","first_name_ar":"سليمان","last_name":"Frangieh","last_name_ar":"فرنجية","gender":"Male","gender_ar":"ذكر","phone":"05-920720/06-662060","fax":"","mobile":"03-272133 (Assist)","email":"","district":"Zgharta","facebook":"","twitter":"https://twitter.com/sleimanfrangieh","deputies_terms":"1992, 1996, 2000, 2009","party":"Marada Movement","party_ar":"تيار المردة","sect":"Maronite","born_day":"18","born_month":"10","born_year":"1965","website":"http://www.elmarada.org/","other_notes":""},{"first_name":"Salim","first_name_ar":"سليم","last_name":"Karam","last_name_ar":"كرم","gender":"Male","gender_ar":"ذكر","phone":"","fax":"","mobile":"03-648700","email":"","district":"Zgharta","facebook":"","twitter":"","deputies_terms":"1996, 2009","party":"Marada Movement","party_ar":"تيار المردة","sect":"Maronite","born_day":"21","born_month":"5","born_year":"1946","website":"","other_notes":""},{"first_name":"Estephan","first_name_ar":"إسطفان","last_name":"Douaihy","last_name_ar":"دويهي","gender":"Male","gender_ar":"ذكر","phone":"","fax":"","mobile":"03-779988","email":"","district":"Zgharta","facebook":"","twitter":"","deputies_terms":"1992, 1996, 2009","party":"Marada Movement","party_ar":"تيار المردة","sect":"Maronite","born_day":"10","born_month":"1","born_year":"1953","website":"","other_notes":""},{"first_name":"Nabih","first_name_ar":"نبيه ","last_name":"Berri","last_name_ar":"بري","gender":"Male","gender_ar":"ذكر","phone":"","fax":"","mobile":"","email":"  President@lp.gov.lb","district":"Zahrani","facebook":"https://www.facebook.com/nberri","twitter":"https://twitter.com/Presidant_Berry","deputies_terms":"1992, 1996, 2000, 2005, 2009","party":"Amal Movement","party_ar":"حركة أمل","sect":"Shia","born_day":"28","born_month":"1","born_year":"1938","website":"http://www.nabihberry.com","other_notes":""},{"first_name":"Ali","first_name_ar":"علي","last_name":"Osseiran","last_name_ar":"عسيران","gender":"Male","gender_ar":"ذكر","phone":"07-990551/07-990 552/01-982100 ext 2223","fax":"07-725290","mobile":"03-855134","email":"","district":"Zahrani","facebook":"","twitter":"","deputies_terms":"1992, 1996, 2000, 2005, 2009","party":"Amal Movement","party_ar":"حركة أمل","sect":"Shia","born_day":"6","born_month":"8","born_year":"1946","website":"","other_notes":""},{"first_name":"Michel","first_name_ar":"ميشال","last_name":"Moussa","last_name_ar":"موسى","gender":"Male","gender_ar":"ذكر","phone":"07-200333/01-982100 ext 2709","fax":"","mobile":"03-245333","email":"","district":"Zahrani","facebook":"","twitter":"","deputies_terms":"1992, 1996, 2000, 2005, 2009","party":"Amal Movement","party_ar":"حركة أمل","sect":"Greek Catholic","born_day":"19","born_month":"9","born_year":"1949","website":"","other_notes":""},{"first_name":"Okab ","first_name_ar":"عقاب","last_name":"Sakr","last_name_ar":"صقر","gender":"Male","gender_ar":"ذكر","phone":"","fax":"","mobile":"03-328233","email":"","district":"Zahleh","facebook":"","twitter":"","deputies_terms":"2009","party":"Lebanon first and Zahle Block","party_ar":"","sect":"Shia","born_day":"null","born_month":"null","born_year":"1975","website":"","other_notes":""},{"first_name":"Elie ","first_name_ar":"إيلي","last_name":"Marouni","last_name_ar":"ماروني","gender":"Male","gender_ar":"ذكر","phone":"","fax":"","mobile":"","email":"eliemarouni1@hotmail.com","district":"Zahleh","facebook":"","twitter":"","deputies_terms":"2009","party":"Kataeb and Zahle Block","party_ar":"","sect":"Maronite","born_day":"null","born_month":"null","born_year":"1964","website":"","other_notes":""},{"first_name":"Joseph ","first_name_ar":"جوزف","last_name":"Maalouf","last_name_ar":"معلوف","gender":"Male","gender_ar":"ذكر","phone":"","fax":"","mobile":"03-328233","email":"","district":"Zahleh","facebook":"","twitter":"https://twitter.com/MPJMaalouf","deputies_terms":"2009","party":"Lebanese Forces and Zahle Block","party_ar":"","sect":"Greek Orthodox","born_day":"null","born_month":"null","born_year":"1960","website":"http://www.josephmaalouf.com","other_notes":""},{"first_name":"Nicolas ","first_name_ar":"نقولا","last_name":"Fattouche","last_name_ar":"فتوش","gender":"Male","gender_ar":"ذكر","phone":"","fax":"","mobile":"","email":"","district":"Zahleh","facebook":"https://www.facebook.com/pages/Nicolas-Fattouch%D9%86%D9%82%D9%88%D9%84%D8%A7-%D9%81%D8%AA%D9%88%D8%B4/311911688913467","twitter":"","deputies_terms":"2009","party":"Zahle In our Hearts Bloc","party_ar":"زحله بالقلب","sect":"Greek Catholic","born_day":"1","born_month":"1","born_year":"1943","website":"","other_notes":""},{"first_name":"Shant ","first_name_ar":"شانت","last_name":"Jinjinian","last_name_ar":"جنيجيان","gender":"Male","gender_ar":"ذكر","phone":"","fax":"","mobile":"03-856641","email":"","district":"Zahleh","facebook":"https://www.facebook.com/shantchinchinian","twitter":"https://twitter.com/SChinchinian","deputies_terms":"2009","party":"Lebanese Forces and Zahle Block","party_ar":"","sect":"Armenian Orthodox","born_day":"null","born_month":"null","born_year":"1974","website":"http://www.chinchinian.info","other_notes":""},{"first_name":"Jamal ","first_name_ar":"جمال","last_name":"Jarrah","last_name_ar":"جراح","gender":"Male","gender_ar":"ذكر","phone":"08-542144","fax":"","mobile":"03-760080","email":"","district":"West Beqaa/Rashaya","facebook":"","twitter":"","deputies_terms":"2009","party":"Future Movement","party_ar":"تيار المستقبل","sect":"Sunni","born_day":"null","born_month":"null","born_year":"1956","website":"","other_notes":""},{"first_name":"Ziad ","first_name_ar":"زياد","last_name":"El Kadiri","last_name_ar":"القادري","gender":"Male","gender_ar":"ذكر","phone":"","fax":"","mobile":"03-411411","email":"","district":"West Beqaa/Rashaya","facebook":"https://www.facebook.com/pages/MP-ZIAD-NAZEM-ALKADRI-Official-Page/188526980768","twitter":"","deputies_terms":"2009","party":"Future Movement","party_ar":"تيار المستقبل","sect":"Sunni","born_day":"null","born_month":"null","born_year":"1979","website":"","other_notes":""},{"first_name":"Amine ","first_name_ar":"أمين","last_name":"Wehbeh","last_name_ar":"وهبة","gender":"Male","gender_ar":"ذكر","phone":"","fax":"","mobile":"03-687784","email":"","district":"West Beqaa/Rashaya","facebook":"","twitter":"https://twitter.com/AmineWehbe","deputies_terms":"2009","party":"Democratic Left Movement","party_ar":"حركة اليسار الديمقراطي","sect":"Shia","born_day":"null","born_month":"null","born_year":"1952","website":"","other_notes":""},{"first_name":"Robert ","first_name_ar":"روبير","last_name":"Ghanem","last_name_ar":"غانم","gender":"Male","gender_ar":"ذكر","phone":"05-456352","fax":"05-456365","mobile":"03-776999 (Assist)","email":"ghanemr@dm.net.lb","district":"West Beqaa/Rashaya","facebook":"","twitter":"","deputies_terms":"1992, 1996, 2000, 2005, 2009","party":"Independent within March 14","party_ar":"مستقل مع ١٤ آذار","sect":"Maronite","born_day":"18","born_month":"6","born_year":"1942","website":"","other_notes":""},{"first_name":"Antoine ","first_name_ar":"أنطوان","last_name":"Saad","last_name_ar":"سعد","gender":"Male","gender_ar":"ذكر","phone":"01-982100","fax":"","mobile":"03-838000 (Assist)","email":"","district":"West Beqaa/Rashaya","facebook":"","twitter":"","deputies_terms":"2009","party":"Progressive Socialist Party","party_ar":"الحزب التقدمي الاشتراكي","sect":"Greek Orthodox","born_day":"null","born_month":"null","born_year":"1937","website":"","other_notes":""},{"first_name":"Wael ","first_name_ar":"وائل","last_name":"Abou Faour","last_name_ar":"أبو فاعور","gender":"Male","gender_ar":"ذكر","phone":"","fax":"","mobile":"03-611403","email":"wafaour@lp.gov.lb","district":"West Beqaa/Rashaya","facebook":"","twitter":"","deputies_terms":"2005, 2009","party":"Progressive Socialist Party","party_ar":"الحزب التقدمي الاشتراكي","sect":"Druze","born_day":"null","born_month":"null","born_year":"1972","website":"","other_notes":""},{"first_name":"Mohammad","first_name_ar":"محمد","last_name":"Safadi","last_name_ar":"الصفدي","gender":"Male","gender_ar":"ذكر","phone":"01-339110/01-219014/01-371179","fax":"01-337628/06-205660","mobile":"03-871780","email":"msafadi@sgh.com.lb","district":"Tripoli","facebook":"","twitter":"","deputies_terms":"2000, 2005, 2009","party":"Tripoli Bloc","party_ar":"التكتل الطرابلسي","sect":"Sunni","born_day":"28","born_month":"3","born_year":"1944","website":"http://www.mohammad-safadi.com/mhm/web.php?idC=10","other_notes":""},{"first_name":"Najib","first_name_ar":"نجيب","last_name":"Mikati","last_name_ar":"ميقاتي","gender":"Male","gender_ar":"ذكر","phone":"01-790111/05-459670/01-982100","fax":"01-860503","mobile":"03-222828","email":"nmikati@najibmikati.org","district":"Tripoli","facebook":"https://www.facebook.com/NajibMikati","twitter":"https://twitter.com/Najib_Mikati","deputies_terms":"2000, 2009","party":"Tripolitan Solidarity Bloc","party_ar":"","sect":"Sunni","born_day":"24","born_month":"12","born_year":"1955","website":"http://www.najibmikati.net/","other_notes":""},{"first_name":"Ahmad","first_name_ar":"أحمد","last_name":"Karami","last_name_ar":"كرامي","gender":"Male","gender_ar":"ذكر","phone":"","fax":"","mobile":"03-239471","email":"","district":"Tripoli","facebook":"","twitter":"","deputies_terms":"1996, 2000, 2009","party":"Tripolitan Solidarity Bloc","party_ar":"","sect":"Sunni","born_day":"28","born_month":"8","born_year":"1944","website":"","other_notes":""},{"first_name":"Samir","first_name_ar":"سمير","last_name":"El Jisr","last_name_ar":"الجسر","gender":"Male","gender_ar":"ذكر","phone":"01-425670","fax":"","mobile":"03-527853","email":"","district":"Tripoli","facebook":"","twitter":"https://twitter.com/samir_jisr","deputies_terms":"1996, 2005, 2009","party":"Future Movement","party_ar":"تيار المستقبل","sect":"Sunni","born_day":"null","born_month":"null","born_year":"1944","website":"","other_notes":""},{"first_name":"Mohammad","first_name_ar":"محمد","last_name":"Kabbara","last_name_ar":"كبارة","gender":"Male","gender_ar":"ذكر","phone":"06-434400/06-443070/06-201201/06-202202/06-600700","fax":"06-436000","mobile":"03-730700","email":"makabbara@hotmail.com","district":"Tripoli","facebook":"https://www.facebook.com/pages/Mohammad-Abdellatif-Kabbara/10746751765","twitter":"https://twitter.com/KabbaraMohammad","deputies_terms":"1992, 1996, 2000, 2009","party":"Independent within 14 March","party_ar":"مستقل مع ١٤ آذار","sect":"Sunni","born_day":"18","born_month":"10","born_year":"1944","website":"","other_notes":""},{"first_name":"Samer","first_name_ar":"سامر","last_name":"Saadeh","last_name_ar":"سعادة","gender":"Male","gender_ar":"ذكر","phone":"","fax":"","mobile":"03-444448","email":"","district":"Tripoli","facebook":"","twitter":"https://twitter.com/samer_saade","deputies_terms":"2009","party":"Kataeb Party","party_ar":"حزب الكتائب اللبنانية","sect":"Maronite","born_day":"null","born_month":"null","born_year":"1976","website":"","other_notes":""},{"first_name":"Robert","first_name_ar":"روبير","last_name":"Fadel","last_name_ar":"فاضل","gender":"Male","gender_ar":"ذكر","phone":"","fax":"","mobile":"03-835108","email":"","district":"Tripoli","facebook":"https://www.facebook.com/RobertFadelPage","twitter":"","deputies_terms":"2009","party":"Independent within 14 March","party_ar":"مستقل مع ١٤ آذار","sect":"Greek Orthodox","born_day":"12","born_month":"1","born_year":"1970","website":"http://www.robertfadel.com/english/Home","other_notes":""},{"first_name":"Badr","first_name_ar":"بدر","last_name":"Wannous","last_name_ar":"ونوس","gender":"Male","gender_ar":"ذكر","phone":"","fax":"","mobile":"03-260747","email":"","district":"Tripoli","facebook":"","twitter":"","deputies_terms":"2005, 2009","party":"Future Movement","party_ar":"تيار المستقبل","sect":"Alawite","born_day":"null","born_month":"null","born_year":"1941","website":"","other_notes":""},{"first_name":"Ali","first_name_ar":"علي","last_name":"Khreis","last_name_ar":"خريس","gender":"Male","gender_ar":"ذكر","phone":"07-742033","fax":"","mobile":"03-644174","email":"","district":"Sour","facebook":"","twitter":"","deputies_terms":"1996, 2000, 2005, 2009","party":"Amal Movement","party_ar":"حركة أمل","sect":"Shia","born_day":"19","born_month":"12","born_year":"1957","website":"","other_notes":""},{"first_name":"Abdelmajid","first_name_ar":"عبد المجيد","last_name":"Saleh","last_name_ar":"صالح","gender":"Male","gender_ar":"ذكر","phone":"01-982100","fax":"","mobile":"03-590356","email":"","district":"Sour","facebook":"","twitter":"","deputies_terms":"1996, 2005, 2009","party":"Amal Movement","party_ar":"حركة أمل","sect":"Shia","born_day":"null","born_month":"null","born_year":"1948","website":"","other_notes":""},{"first_name":"Mohammad","first_name_ar":"محمد","last_name":"Fneish","last_name_ar":"فنيش","gender":"Male","gender_ar":"ذكر","phone":"01-279393","fax":"","mobile":"","email":"","district":"Sour","facebook":"","twitter":"","deputies_terms":"1992, 1996, 2000, 2005, 2009","party":"Hezbollah","party_ar":"حزب الله","sect":"Shia","born_day":"10","born_month":"2","born_year":"1953","website":"","other_notes":""},{"first_name":"Nawwaf","first_name_ar":"نواف","last_name":"Moussawi","last_name_ar":"موسوي","gender":"Male","gender_ar":"ذكر","phone":"","fax":"","mobile":"","email":"","district":"Sour","facebook":"","twitter":"","deputies_terms":"2009","party":"Hezbollah","party_ar":"حزب الله","sect":"Shia","born_day":"null","born_month":"null","born_year":"1965","website":"","other_notes":""},{"first_name":"Fouad","first_name_ar":"فؤاد","last_name":"Siniora","last_name_ar":"سنيورة","gender":"Male","gender_ar":"ذكر","phone":"01-642720","fax":"","mobile":"","email":"","district":"Saida","facebook":"","twitter":"https://twitter.com/SinioraFuad","deputies_terms":"2009","party":"Future Movement","party_ar":"تيار المستقبل","sect":"Sunni","born_day":"null","born_month":"null","born_year":"1943","website":"","other_notes":""},{"first_name":"Abdellatif ","first_name_ar":"عبد اللطيف","last_name":"Zein","last_name_ar":"زين","gender":"Male","gender_ar":"ذكر","phone":"01-800150/01-987654 off 412","fax":"","mobile":"","email":"","district":"Nabatieh","facebook":"","twitter":"","deputies_terms":"1960, 1964, 1968, 1972, 1992, 1996, 2000, 2005, 2009","party":"Amal Movement","party_ar":"حركة أمل","sect":"Shia","born_day":"null","born_month":"null","born_year":"1932","website":"","other_notes":""},{"first_name":"Yassine ","first_name_ar":"ياسين","last_name":"Jaber","last_name_ar":"جابر","gender":"Male","gender_ar":"ذكر","phone":"01-808770","fax":"01-802080","mobile":"03-380800","email":"sigmalb@cyberia.net.lb","district":"Nabatieh","facebook":"","twitter":"","deputies_terms":"1992, 1996, 2000, 2005, 2009","party":"Amal Movement","party_ar":"حركة أمل","sect":"Shia","born_day":"null","born_month":"null","born_year":"1951","website":"","other_notes":""},{"first_name":"Mohammad ","first_name_ar":"محمد","last_name":"Raad","last_name_ar":"رعد","gender":"Male","gender_ar":"ذكر","phone":"01-271853/01-210101","fax":"","mobile":"03-610609","email":"","district":"Nabatieh","facebook":"","twitter":"","deputies_terms":"1992, 1996, 2000, 2005, 2009","party":"Hezbollah","party_ar":"حزب الله","sect":"Shia","born_day":"22","born_month":"8","born_year":"1955","website":"","other_notes":""},{"first_name":"Ibrahim","first_name_ar":"إبراهيم","last_name":"Kanaan","last_name_ar":"كنعان","gender":"Male","gender_ar":"ذكر","phone":"01-982100","fax":"","mobile":"03-338812","email":"Ikanaanoffice@gmail.com","district":"Metn","facebook":"https://www.facebook.com/ibrahimkanaan.official","twitter":"https://twitter.com/IbrahimKanaan","deputies_terms":"2005, 2009","party":"Free Patriotic Movement","party_ar":"التيار الوطني الحر","sect":"Maronite","born_day":"null","born_month":"null","born_year":"1962","website":"http://www.ibrahimkanaan.org","other_notes":""},{"first_name":"Nabil","first_name_ar":"نبيل","last_name":"Nicolas","last_name_ar":"نقولا","gender":"Male","gender_ar":"ذكر","phone":"","fax":"","mobile":"03-157762","email":"","district":"Metn","facebook":"https://www.facebook.com/dr.nabil.nicolas","twitter":"","deputies_terms":"2005, 2009","party":"Free Patriotic Movement","party_ar":"التيار الوطني الحر","sect":"Maronite","born_day":"14","born_month":"9","born_year":"1950","website":"","other_notes":""},{"first_name":"Salim","first_name_ar":"سليم","last_name":"Salhab","last_name_ar":"سلهب","gender":"Male","gender_ar":"ذكر","phone":"","fax":"","mobile":"03-616633","email":"","district":"Metn","facebook":"","twitter":"","deputies_terms":"1992, 2005, 2009","party":"Free Patriotic Movement","party_ar":"التيار الوطني الحر","sect":"Maronite","born_day":"null","born_month":"null","born_year":"1945","website":"","other_notes":""},{"first_name":"Samy","first_name_ar":"سامي","last_name":"Gemayel","last_name_ar":"جميل","gender":"Male","gender_ar":"ذكر","phone":"","fax":"","mobile":"03-554444","email":"","district":"Metn","facebook":"https://www.facebook.com/SamyGemayel","twitter":"https://twitter.com/samygemayel","deputies_terms":"2009","party":"Kataeb Party","party_ar":"حزب الكتائب اللبنانية","sect":"Maronite","born_day":"null","born_month":"null","born_year":"1980","website":"http://samygemayel.com/","other_notes":""},{"first_name":"Ghassan","first_name_ar":"غسان","last_name":"Moukheiber","last_name_ar":"مخيبر","gender":"Male","gender_ar":"ذكر","phone":"01-331210/03-775222","fax":"01-201081","mobile":"03-775222","email":"gem@inco.com.lb","district":"Metn","facebook":"https://www.facebook.com/groups/16930781636/?fref=ts","twitter":"https://twitter.com/Ghassanem","deputies_terms":"2002, 2005, 2009","party":"Free Patriotic Movement","party_ar":"التيار الوطني الحر","sect":"Greek Orthodox","born_day":"8","born_month":"12","born_year":"1958","website":"http://ghassanmoukheiber.com/","other_notes":"He started in 2002 in an election after his uncle died "},{"first_name":"Michel","first_name_ar":"ميشال","last_name":"Murr","last_name_ar":"المر","gender":"Male","gender_ar":"ذكر","phone":"04-404214/04-270000/04-271000/01-427774/04-406000","fax":"","mobile":"","email":"admin@michelmurr.com","district":"Metn","facebook":"","twitter":"","deputies_terms":"1968, 1992, 1996, 2000, 2005, 2009","party":"Independent","party_ar":"مستقل","sect":"Greek Orthodox","born_day":"null","born_month":"null","born_year":"1932","website":"http://www.michelmurr.com/","other_notes":"We will exclude the 1991 appointment time as deputy"},{"first_name":"Edgard","first_name_ar":"إدغار","last_name":"Maalouf","last_name_ar":"معلوف","gender":"Male","gender_ar":"ذكر","phone":"04-405402","fax":"","mobile":"03-129214","email":"aboul_ed@hotmail.com","district":"Metn","facebook":"","twitter":"","deputies_terms":"2005, 2009","party":"Free Patriotic Movement","party_ar":"التيار الوطني الحر","sect":"Greek Catholic","born_day":"null","born_month":"null","born_year":"1934","website":"","other_notes":""},{"first_name":"Hagop","first_name_ar":"هاغوب","last_name":"Pakradounian","last_name_ar":"بقرادونيان","gender":"Male","gender_ar":"ذكر","phone":"01-982100","fax":"","mobile":"03-397766","email":"","district":"Metn","facebook":"","twitter":"","deputies_terms":"2005, 2009","party":"Tashnag","party_ar":"الإتحاد الثوري الأرمني - الطاشناق","sect":"Armenian Orthodox","born_day":"null","born_month":"null","born_year":"1956","website":"","other_notes":""},{"first_name":"Farid ","first_name_ar":"فريد","last_name":"Makari","last_name_ar":"مكاري","gender":"Male","gender_ar":"ذكر","phone":"04-403507/01-989818/04-403472/04-521252/06-541644/01-982100 ext 2212","fax":"04-521252","mobile":"03-547547","email":"","district":"Koura","facebook":"https://www.facebook.com/makarifarid","twitter":"","deputies_terms":"1992, 1996, 2000, 2005, 2009","party":"Future Movement","party_ar":"تيار المستقبل","sect":"Greek Orthodox","born_day":"24","born_month":"10","born_year":"1947","website":"http://www.faridmakari.com/","other_notes":""},{"first_name":"Nicolas","first_name_ar":"نقولا","last_name":"Ghosn","last_name_ar":"غصن","gender":"Male","gender_ar":"ذكر","phone":"06-950053","fax":"","mobile":"03-300396","email":"","district":"Koura","facebook":"","twitter":"","deputies_terms":"1996, 2005, 2009","party":"Future Movement","party_ar":"تيار المستقبل","sect":"Greek Orthodox","born_day":"null","born_month":"null","born_year":"1940","website":"","other_notes":""},{"first_name":"Farid ","first_name_ar":"فريد","last_name":"Habib","last_name_ar":"حبيب","gender":"Male","gender_ar":"ذكر","phone":"01-982100","fax":"","mobile":"","email":"","district":"Koura","facebook":"","twitter":"","deputies_terms":"2005, 2009","party":"Lebanese Forces","party_ar":"القوات اللبنانية","sect":"Greek Orthodox","born_day":"null","born_month":"null","born_year":"1935","website":"","other_notes":"Passed away May 2012"},{"first_name":"Fadi","first_name_ar":"فادي","last_name":"Karam","last_name_ar":"كرم","gender":"Male","gender_ar":"ذكر","phone":"06-954385","fax":"","mobile":"","email":"","district":"Koura","facebook":"https://www.facebook.com/DrFadyKaram","twitter":"https://twitter.com/drFadiKaram","deputies_terms":"2009","party":"Lebanese Forces","party_ar":"القوات اللبنانية","sect":"Greek Orthodox","born_day":"null","born_month":"null","born_year":"1961","website":"","other_notes":"Replacing F.Habib "},{"first_name":"Michel","first_name_ar":"ميشال","last_name":"Aoun","last_name_ar":"عون","gender":"Male","gender_ar":"ذكر","phone":"01-982100","fax":"","mobile":"03-191918","email":"","district":"Kesserwan","facebook":"https://www.facebook.com/Gen.M.AOUN","twitter":"https://twitter.com/General_Aoun","deputies_terms":"2005, 2009","party":"Free Patriotic Movement","party_ar":"التيار الوطني الحر","sect":"Maronite","born_day":"30","born_month":"9","born_year":"1933","website":"","other_notes":""},{"first_name":"Neemtallah","first_name_ar":"نعمة الله","last_name":"Abi Nasr","last_name_ar":"أبي نصر","gender":"Male","gender_ar":"ذكر","phone":"09-935856","fax":"","mobile":"03-671673","email":"","district":"Kesserwan","facebook":"","twitter":"","deputies_terms":"2000, 2009","party":"Free Patriotic Movement","party_ar":"التيار الوطني الحر","sect":"Maronite","born_day":"null","born_month":"null","born_year":"1936","website":"","other_notes":""},{"first_name":"Youssef","first_name_ar":"يوسف","last_name":"Khalil","last_name_ar":"خليل","gender":"Male","gender_ar":"ذكر","phone":"09-952120","fax":"","mobile":"","email":"","district":"Kesserwan","facebook":"https://www.facebook.com/groups/68556748447/","twitter":"","deputies_terms":"2005, 2009","party":"Free Patriotic Movement","party_ar":"التيار الوطني الحر","sect":"Maronite","born_day":"null","born_month":"null","born_year":"1947","website":"","other_notes":""},{"first_name":"Farid ","first_name_ar":"فريد","last_name":"El Khazen","last_name_ar":"الخازن","gender":"Male","gender_ar":"ذكر","phone":"01-982100","fax":"","mobile":"03-741874","email":"","district":"Kesserwan","facebook":"https://www.facebook.com/faridhaykalelkhazen","twitter":"https://twitter.com/FaridHaykalElKh","deputies_terms":"2005, 2009","party":"Free Patriotic Movement","party_ar":"التيار الوطني الحر","sect":"Maronite","born_day":"null","born_month":"null","born_year":"1960","website":"http://www.farideelkhazen.com/","other_notes":""},{"first_name":"Ziad","first_name_ar":"زياد","last_name":"Aswad","last_name_ar":"أسود","gender":"Male","gender_ar":"ذكر","phone":"","fax":"","mobile":"","email":"","district":"Jezzine","facebook":"","twitter":"","deputies_terms":"2005, 2009","party":"Free Patriotic Movement","party_ar":"التيار الوطني الحر","sect":"Maronite","born_day":"null","born_month":"null","born_year":"1968","website":"","other_notes":""},{"first_name":"Michel ","first_name_ar":"ميشال","last_name":"Helou","last_name_ar":"حلو","gender":"Male","gender_ar":"ذكر","phone":"","fax":"","mobile":"","email":"","district":"Jezzine","facebook":"","twitter":"","deputies_terms":"2009","party":"Free Patriotic Movement","party_ar":"التيار الوطني الحر","sect":"Maronite","born_day":"null","born_month":"null","born_year":"1949","website":"","other_notes":""},{"first_name":"Issam","first_name_ar":"عصام","last_name":"Sawaya","last_name_ar":"صوايا","gender":"Male","gender_ar":"ذكر","phone":"","fax":"","mobile":"","email":"","district":"Jezzine","facebook":"","twitter":"","deputies_terms":"2009","party":"Free Patriotic Movement","party_ar":"التيار الوطني الحر","sect":"Greek Catholic","born_day":"null","born_month":"null","born_year":"1942","website":"","other_notes":""},{"first_name":"Abbas ","first_name_ar":"عباس","last_name":"Hachem","last_name_ar":"هاشم","gender":"Male","gender_ar":"ذكر","phone":"01-868177","fax":"01-868269","mobile":"03-315706","email":"abbas_hachem@macktoub.com","district":"Jbeil","facebook":"","twitter":"","deputies_terms":"2000, 2005, 2009","party":"Free Patriotic Movement","party_ar":"التيار الوطني الحر","sect":"Shia","born_day":"25","born_month":"12","born_year":"1954","website":"","other_notes":""},{"first_name":"Walid","first_name_ar":"وليد","last_name":"Khoury","last_name_ar":"خوري","gender":"Male","gender_ar":"ذكر","phone":"","fax":"","mobile":"03-212666","email":"","district":"Jbeil","facebook":"","twitter":"","deputies_terms":"2005, 2009","party":"Free Patriotic Movement","party_ar":"التيار الوطني الحر","sect":"Maronite","born_day":"null","born_month":"null","born_year":"1955","website":"","other_notes":""},{"first_name":"Simon","first_name_ar":"سيمون","last_name":"Abi Ramia","last_name_ar":"أبي رميا","gender":"Male","gender_ar":"ذكر","phone":"","fax":"","mobile":"03-035902","email":"","district":"Jbeil","facebook":"","twitter":"https://twitter.com/SimonAbiramia","deputies_terms":"2009","party":"Free Patriotic Movement","party_ar":"التيار الوطني الحر","sect":"Maronite","born_day":"6","born_month":"3","born_year":"1965","website":"http://www.simonabiramia.com/Home.aspx","other_notes":""},{"first_name":"Kassem ","first_name_ar":"قاسم","last_name":"Hachem","last_name_ar":"هاشم","gender":"Male","gender_ar":"ذكر","phone":"08-506010","fax":"08-506506","mobile":"03-252075","email":"","district":"Hasbaya/Marjeyoun","facebook":"","twitter":"","deputies_terms":"2000, 2005, 2009","party":"Arab Socialist Ba'ath Party of Lebanon","party_ar":"حزب البعث العربي الاشتراكي في لبنان","sect":"Sunni","born_day":"6","born_month":"8","born_year":"1960","website":"","other_notes":""},{"first_name":"Ali ","first_name_ar":"علي","last_name":"Hassan Khalil","last_name_ar":"حسن خليل","gender":"Male","gender_ar":"ذكر","phone":"01-840171","fax":"01-840177","mobile":"03-632629","email":"","district":"Hasbaya/Marjeyoun","facebook":"","twitter":"https://twitter.com/alihasankhalil","deputies_terms":"1996, 2000, 2005, 2009","party":"Amal Movement","party_ar":"حركة أمل","sect":"Shia","born_day":"14","born_month":"7","born_year":"1964","website":"","other_notes":""},{"first_name":"Ali ","first_name_ar":"علي","last_name":"Fayyad","last_name_ar":"فياض","gender":"Male","gender_ar":"ذكر","phone":"","fax":"","mobile":"","email":"","district":"Hasbaya/Marjeyoun","facebook":"","twitter":"","deputies_terms":"2009","party":"Hezbollah","party_ar":"حزب الله","sect":"Shia","born_day":"null","born_month":"null","born_year":"1962","website":"","other_notes":""},{"first_name":"Assaad ","first_name_ar":"أسعد","last_name":"Hardan","last_name_ar":"حردان","gender":"Male","gender_ar":"ذكر","phone":"04-295400","fax":"","mobile":"","email":"","district":"Hasbaya/Marjeyoun","facebook":"","twitter":"","deputies_terms":"1992, 1996, 2000, 2005, 2009","party":"Syrian Social Nationalist Party","party_ar":"الحزب السوري القومي الاجتماعي","sect":"Greek Orthodox","born_day":"31","born_month":"7","born_year":"1951","website":"","other_notes":""},{"first_name":"Anwar ","first_name_ar":"أنور","last_name":"Khalil","last_name_ar":"الخليل","gender":"Male","gender_ar":"ذكر","phone":"01-809970","fax":"01-810973","mobile":"03 368555","email":"akhalil@cyberia.net.lb","district":"Hasbaya/Marjeyoun","facebook":"","twitter":"","deputies_terms":"1992, 1996, 2000, 2005, 2009","party":"Amal Movement","party_ar":"حركة أمل","sect":"Druze","born_day":"null","born_month":"null","born_year":"1938","website":"","other_notes":""},{"first_name":"Ahmad","first_name_ar":"أحمد","last_name":"Fatfat","last_name_ar":"فتفت","gender":"Male","gender_ar":"ذكر","phone":"06-490492","fax":"06-490535","mobile":"03-747019","email":"FATAHMP@cyberia.net.lb","district":"Dinniyeh & Minieh","facebook":"https://www.facebook.com/pages/Dr-Ahmad-Fatfat/375538362538794","twitter":"","deputies_terms":"1996, 2000, 2005, 2009","party":"Future Movement","party_ar":"تيار المستقبل","sect":"Sunni","born_day":"28","born_month":"3","born_year":"1953","website":"http://www.ahmadfatfat.com/ar/","other_notes":""},{"first_name":"Kassem","first_name_ar":"قاسم","last_name":"Abdulaziz","last_name_ar":"عبد العزيز","gender":"Male","gender_ar":"ذكر","phone":"06-611700","fax":"","mobile":"03-613777","email":"","district":"Dinniyeh & Minieh","facebook":"","twitter":"","deputies_terms":"2005, 2009","party":"Tripoli Bloc","party_ar":"التكتل الطرابلسي","sect":"Sunni","born_day":"null","born_month":"null","born_year":"1951","website":"","other_notes":""},{"first_name":"Alaeddine","first_name_ar":"علاء الدين","last_name":"Terro","last_name_ar":"ترو","gender":"Male","gender_ar":"ذكر","phone":"07-623344","fax":"07-623340","mobile":"03-437537","email":"","district":"Chouf","facebook":"","twitter":"","deputies_terms":"1992, 1996, 2000, 2005, 2009","party":"Progressive Socialist Party","party_ar":"الحزب التقدمي الاشتراكي","sect":"Sunni","born_day":"5","born_month":"11","born_year":"1953","website":"","other_notes":""},{"first_name":"Ibrahim","first_name_ar":"إبراهيم","last_name":"Najjar","last_name_ar":"نجار","gender":"Male","gender_ar":"ذكر","phone":"","fax":"","mobile":"","email":"","district":"Chouf","facebook":"","twitter":"","deputies_terms":"2005, 2009","party":"Future Movement","party_ar":"تيار المستقبل","sect":"Sunni","born_day":"null","born_month":"null","born_year":"1941","website":"","other_notes":""},{"first_name":"Elie","first_name_ar":"إيلي","last_name":"Aoun","last_name_ar":"عون","gender":"Male","gender_ar":"ذكر","phone":"01-480183","fax":"01-381859","mobile":"03-664382","email":"","district":"Chouf","facebook":"","twitter":"https://twitter.com/ElieAounLeader","deputies_terms":"2000, 2005, 2009","party":"Progressive Socialist Party","party_ar":"الحزب التقدمي الاشتراكي","sect":"Maronite","born_day":"null","born_month":"null","born_year":"1939","website":"","other_notes":""},{"first_name":"Dory","first_name_ar":"دوري","last_name":"Chamoun","last_name_ar":"شمعون","gender":"Male","gender_ar":"ذكر","phone":"","fax":"","mobile":"03-890022","email":"","district":"Chouf","facebook":"","twitter":"","deputies_terms":"2009","party":"National Liberal Party","party_ar":"حزب الوطنيين الأحرار","sect":"Maronite","born_day":"8","born_month":"11","born_year":"1931","website":"","other_notes":""},{"first_name":"Georges","first_name_ar":"جورج","last_name":"Adwan","last_name_ar":"عدوان","gender":"Male","gender_ar":"ذكر","phone":"01-982100","fax":"","mobile":"","email":"","district":"Chouf","facebook":"","twitter":"","deputies_terms":"2005, 2009","party":"Lebanese Forces","party_ar":"القوات اللبنانية","sect":"Maronite","born_day":"null","born_month":"null","born_year":"1947","website":"","other_notes":""},{"first_name":"Nehme","first_name_ar":"نعمه","last_name":"Tohme","last_name_ar":"طعمة","gender":"Male","gender_ar":"ذكر","phone":"04-525295/04-521180/04-521190","fax":"","mobile":"","email":"","district":"Chouf","facebook":"","twitter":"","deputies_terms":"2000, 2005, 2009","party":"Progressive Socialist Party","party_ar":"الحزب التقدمي الاشتراكي","sect":"Greek Catholic","born_day":"null","born_month":"null","born_year":"1934","website":"","other_notes":""},{"first_name":"Walid","first_name_ar":"وليد","last_name":"Jumblatt","last_name_ar":"جنبلاط","gender":"Male","gender_ar":"ذكر","phone":"05-311555","fax":"","mobile":"","email":"alanbaa@live.com","district":"Chouf","facebook":"https://www.facebook.com/Walid.K.Jumblat","twitter":"https://twitter.com/walid_jounblat","deputies_terms":"1992, 1996, 2000, 2005, 2009","party":"Progressive Socialist Party","party_ar":"الحزب التقدمي الاشتراكي","sect":"Druze","born_day":"7","born_month":"7","born_year":"1949","website":"","other_notes":""},{"first_name":"Marwan","first_name_ar":"مروان","last_name":"Hamadeh","last_name_ar":"حمادة","gender":"Male","gender_ar":"ذكر","phone":"01-360311","fax":"","mobile":"","email":"","district":"Chouf","facebook":"","twitter":"","deputies_terms":"1992, 1996, 2000, 2005, 2009","party":"Progressive Socialist Party","party_ar":"الحزب التقدمي الاشتراكي","sect":"Druze","born_day":"11","born_month":"9","born_year":"1939","website":"","other_notes":""},{"first_name":"Elie","first_name_ar":"إيلي","last_name":"Keyrouz","last_name_ar":"كيروز","gender":"Male","gender_ar":"ذكر","phone":"09-952120","fax":"","mobile":"03-472447","email":"","district":"Bsharri","facebook":"","twitter":"","deputies_terms":"2005, 2009","party":"Lebanese Forces","party_ar":"القوات اللبنانية","sect":"Maronite","born_day":"null","born_month":"null","born_year":"1947","website":"","other_notes":""},{"first_name":"Ali","first_name_ar":"علي","last_name":"Bazzi","last_name_ar":"بزي","gender":"Male","gender_ar":"ذكر","phone":"07-530555","fax":"01-990800","mobile":"03-424318","email":"alibazzimp@hotmail.com","district":"Bint Jbeil","facebook":"","twitter":"https://twitter.com/DeputyAliBazzi","deputies_terms":"2009","party":"Amal Movement","party_ar":"حركة أمل","sect":"Shia","born_day":"1","born_month":"9","born_year":"1958","website":"","other_notes":""},{"first_name":"Ayoub","first_name_ar":"أيوب","last_name":"Hmayed","last_name_ar":"حميد","gender":"Male","gender_ar":"ذكر","phone":"01-855511","fax":"","mobile":"","email":"","district":"Bint Jbeil","facebook":"","twitter":"","deputies_terms":"1992, 1996, 2000, 2005, 2009","party":"Amal Movement","party_ar":"حركة أمل","sect":"Shia","born_day":"null","born_month":"null","born_year":"1945","website":"","other_notes":""},{"first_name":"Hassan ","first_name_ar":"حسن","last_name":"Fadlallah","last_name_ar":"فضل الله","gender":"Male","gender_ar":"ذكر","phone":"01-982100","fax":"","mobile":"03-663552","email":"","district":"Bint Jbeil","facebook":"","twitter":"","deputies_terms":"2005, 2009","party":"Hezbollah","party_ar":"حزب الله","sect":"Shia","born_day":"null","born_month":"null","born_year":"1967","website":"","other_notes":""},{"first_name":"Saad","first_name_ar":"سعد الدين","last_name":"Hariri","last_name_ar":"الحريري","gender":"Male","gender_ar":"ذكر","phone":"","fax":"","mobile":"","email":"","district":"Beirut III","facebook":"https://www.facebook.com/Saad.R.Hariri","twitter":"https://twitter.com/HaririSaad","deputies_terms":"2005, 2009","party":"Future Movement","party_ar":"تيار المستقبل","sect":"Sunni","born_day":"18","born_month":"5","born_year":"1970","website":"","other_notes":""},{"first_name":"Ammar ","first_name_ar":"عمار","last_name":"Houry","last_name_ar":"حوري","gender":"Male","gender_ar":"ذكر","phone":"01-982100","fax":"","mobile":"","email":"","district":"Beirut III","facebook":"","twitter":"https://twitter.com/Ammarhoury","deputies_terms":"2005, 2009","party":"Future Movement","party_ar":"تيار المستقبل","sect":"Sunni","born_day":"31","born_month":"10","born_year":"1945","website":"","other_notes":""},{"first_name":"Mohamad","first_name_ar":"محمد","last_name":"Kabbani","last_name_ar":"قباني","gender":"Male","gender_ar":"ذكر","phone":"01-801180/01-863601","fax":"01-362770","mobile":"03-645111","email":"","district":"Beirut III","facebook":"","twitter":"","deputies_terms":"1992, 1996, 2000, 2005, 2009","party":"Future Movement","party_ar":"تيار المستقبل","sect":"Sunni","born_day":"18","born_month":"2","born_year":"1942","website":"","other_notes":""},{"first_name":"Tamam","first_name_ar":"تمام","last_name":"Salam","last_name_ar":"سلام","gender":"Male","gender_ar":"ذكر","phone":"","fax":"","mobile":"","email":"team@tammamsalam.net","district":"Beirut III","facebook":"https://www.facebook.com/TammamSalam","twitter":"https://twitter.com/salamTammam","deputies_terms":"1996, 2009","party":"Independent within 14 March","party_ar":"مستقل مع ١٤ آذار","sect":"Sunni","born_day":"13","born_month":"5","born_year":"1945","website":"http://tammamsalam.net/","other_notes":""},{"first_name":"Imad","first_name_ar":"عماد","last_name":"El Hout","last_name_ar":"الحوت","gender":"Male","gender_ar":"ذكر","phone":"01-814047","fax":"","mobile":"03-316737","email":"","district":"Beirut III","facebook":"https://www.facebook.com/IHOUT.MP","twitter":"https://twitter.com/houtimad","deputies_terms":"1996, 2009","party":"Islamic Group","party_ar":"الجماعة الإسلامية","sect":"Sunni","born_day":"22","born_month":"10","born_year":"1962","website":"http://www.imadhout.com","other_notes":""},{"first_name":"Ghazi","first_name_ar":"غازي","last_name":"Youssef","last_name_ar":"يوسف","gender":"Male","gender_ar":"ذكر","phone":"01-987500","fax":"","mobile":"03-444009","email":"","district":"Beirut III","facebook":"","twitter":"","deputies_terms":"2005, 2009","party":"Future Movement","party_ar":"تيار المستقبل","sect":"Shia","born_day":"9","born_month":"3","born_year":"1954","website":"","other_notes":""},{"first_name":"Bassem","first_name_ar":"باسم","last_name":"Chabb","last_name_ar":"الشاب","gender":"Male","gender_ar":"ذكر","phone":"01-982100","fax":"","mobile":"03-319336","email":"","district":"Beirut III","facebook":"","twitter":"","deputies_terms":"2005, 2009","party":"Future Movement","party_ar":"تيار المستقبل","sect":"Protestant","born_day":"27","born_month":"4","born_year":"1957","website":"","other_notes":""},{"first_name":"Atef","first_name_ar":"عاطف","last_name":"Majdalani","last_name_ar":"مجدلاني","gender":"Male","gender_ar":"ذكر","phone":"01-997777","fax":"05-459339","mobile":"03-342424","email":"amajda@inco.com .lb","district":"Beirut III","facebook":"https://www.facebook.com/dratef.majdalani","twitter":"https://twitter.com/AtefMajdalani","deputies_terms":"1996, 2000, 2005, 2009","party":"Future Movement","party_ar":"تيار المستقبل","sect":"Greek Orthodox","born_day":"23","born_month":"3","born_year":"1948","website":"","other_notes":""},{"first_name":"Ghazi","first_name_ar":"غازي","last_name":"Aridi","last_name_ar":"العريضي","gender":"Male","gender_ar":"ذكر","phone":"01-756200","fax":"01-756202 ","mobile":"","email":"info@ghaziaridi.org","district":"Beirut III","facebook":"","twitter":"","deputies_terms":"2000, 2005, 2009","party":"Progressive Socialist Party","party_ar":"الحزب التقدمي الاشتراكي","sect":"Druze","born_day":"17","born_month":"9","born_year":"1954","website":"http://www.ghaziaridi.org","other_notes":""},{"first_name":"Nabil","first_name_ar":"نبيل","last_name":"de Freige","last_name_ar":"دو فريج","gender":"Male","gender_ar":"ذكر","phone":"","fax":"","mobile":"03-618466","email":"ndefreige@cyberia.net.lb","district":"Beirut III","facebook":"","twitter":"","deputies_terms":"2000, 2005, 2009","party":"Future Movement","party_ar":"تيار المستقبل","sect":"Christian minorities","born_day":"31","born_month":"8","born_year":"1955","website":"","other_notes":""},{"first_name":"Nohad","first_name_ar":"نهاد","last_name":"El Machnouk","last_name_ar":"المشنوق","gender":"Male","gender_ar":"ذكر","phone":"01-755 011","fax":"","mobile":"","email":"nmachnouk@nmachnouk.com","district":"Beirut II","facebook":"https://www.facebook.com/NouhadMachnouk","twitter":"https://twitter.com/NohadMachnouk ","deputies_terms":"2009","party":"Future Movement","party_ar":"تيار المستقبل","sect":"Sunni","born_day":"null","born_month":"null","born_year":"1955","website":"http://www.machnouk.com","other_notes":""},{"first_name":"Hani ","first_name_ar":"هاني","last_name":"Kobeissy","last_name_ar":"قبيسي","gender":"Male","gender_ar":"ذكر","phone":"","fax":"","mobile":"03-935000","email":"","district":"Beirut II","facebook":"","twitter":"","deputies_terms":"2005, 2009","party":"Amal Movement","party_ar":"حركة أمل","sect":"Shia","born_day":"10","born_month":"4","born_year":"1959","website":"","other_notes":""},{"first_name":"Arthur","first_name_ar":"أرتيور","last_name":"Nazarian","last_name_ar":"نظريان","gender":"Male","gender_ar":"ذكر","phone":"","fax":"","mobile":"03-619890","email":"","district":"Beirut II","facebook":"","twitter":"","deputies_terms":"2009","party":"Tashnag","party_ar":"الإتحاد الثوري الأرمني - الطاشناق","sect":"Armenian Orthodox","born_day":"null","born_month":"null","born_year":"1951","website":"","other_notes":""},{"first_name":"Sebouh","first_name_ar":"سيبوه","last_name":"Kalbakian","last_name_ar":"قلبقيان","gender":"Male","gender_ar":"ذكر","phone":"","fax":"","mobile":"03-666515","email":"info@hunchak.org","district":"Beirut II","facebook":"https://www.facebook.com/pages/Comrade-Sebouh-Kalpakian/70536058685","twitter":"https://twitter.com/hunchaks","deputies_terms":"1992, 2005, 2009","party":"Hunchak","party_ar":"حزب الهانشاغ","sect":"Armenian Orthodox","born_day":"30","born_month":"9","born_year":"1960","website":"","other_notes":""},{"first_name":"Nadim","first_name_ar":"نديم","last_name":"Gemayel","last_name_ar":"الجميل","gender":"Male","gender_ar":"ذكر","phone":"01-610452","fax":"","mobile":"","email":"media@nadimgemayel.com","district":"Beirut I","facebook":"https://facebook.com/Nadim.Gemayel","twitter":"https://twitter.com/nadimgemayel","deputies_terms":"2009","party":"Kataeb Party","party_ar":"حزب الكتائب","sect":"Maronite","born_day":"1","born_month":"5","born_year":"1982","website":"","other_notes":""},{"first_name":"Michel","first_name_ar":"ميشال","last_name":"Pharaon","last_name_ar":"فرعون","gender":"Male","gender_ar":"ذكر","phone":"01-329000","fax":"01-989000","mobile":"70-681843","email":"info@michelpharaon.com/mpharaon@dm.net.lb","district":"Beirut I","facebook":"","twitter":"","deputies_terms":"1996, 2000, 2005, 2009","party":"Independent within 14 March","party_ar":"مستقل مع ١٤ آذار","sect":"Greek Catholic","born_day":"24","born_month":"6","born_year":"1959","website":"http://www.michelpharaon.com","other_notes":""},{"first_name":"Jean","first_name_ar":"جان","last_name":"Ogassapian","last_name_ar":"أوغاسبيان","gender":"Male","gender_ar":"ذكر","phone":"01-997777","fax":"01-242698","mobile":"03-339635","email":"ogasbian@cyberia.net.lb","district":"Beirut I","facebook":"","twitter":"","deputies_terms":"2000, 2005, 2009","party":"Ramgavar","party_ar":"حزب الرمغافار الديمقراطي الليبرالي الأرمني","sect":"Armenian Orthodox","born_day":"17","born_month":"2","born_year":"1954","website":"","other_notes":""},{"first_name":"Serge","first_name_ar":"سيرج","last_name":"Torsarkissian","last_name_ar":"طورسركيسيان","gender":"Male","gender_ar":"ذكر","phone":"04-710824","fax":"04-710824","mobile":"03-273473","email":"serge_t@cyberia.net.lb","district":"Beirut I","facebook":"","twitter":"","deputies_terms":"2000, 2005, 2009","party":"Hunchak","party_ar":"حزب الهانشاغ","sect":"Armenian Catholic","born_day":"30","born_month":"9","born_year":"1965","website":"","other_notes":""},{"first_name":"Antoine","first_name_ar":"أنطوان","last_name":"Zahra","last_name_ar":"زهرا","gender":"Male","gender_ar":"ذكر","phone":"","fax":"","mobile":"03-350498","email":"","district":"Batroun","facebook":"","twitter":"https://twitter.com/ZahraAntoine","deputies_terms":"2005, 2009","party":"Lebanese Forces","party_ar":"القوات اللبنانية","sect":"Maronite","born_day":"null","born_month":"null","born_year":"1956","website":"","other_notes":""},{"first_name":"Boutros","first_name_ar":"بطرس","last_name":"Harb","last_name_ar":"حرب","gender":"Male","gender_ar":"ذكر","phone":"01-381122","fax":"01-394609","mobile":"03 290333","email":"bharb@cyberia.net.lb","district":"Batroun","facebook":"https://www.facebook.com/BoutrosHarb","twitter":"https://twitter.com/Harb_Boutros","deputies_terms":"1996, 2000, 2005, 2009","party":"Independent within 14 March","party_ar":"مستقل مع ١٤ آذار","sect":"Maronite","born_day":"3","born_month":"7","born_year":"1944","website":"","other_notes":""},{"first_name":"Walid","first_name_ar":"وليد","last_name":"Succariyeh","last_name_ar":"سكرية","gender":"Male","gender_ar":"ذكر","phone":"","fax":"","mobile":"03-725720","email":"","district":"Baalbeck/Hermil","facebook":"","twitter":"","deputies_terms":"2009","party":"Hezbollah","party_ar":"حزب الله","sect":"Sunni","born_day":"null","born_month":"null","born_year":"1948","website":"","other_notes":""},{"first_name":"Kamel ","first_name_ar":"كامل","last_name":"Rifaii","last_name_ar":"رفاعي","gender":"Male","gender_ar":"ذكر","phone":"01-651663/08-371508/08-371848 ","fax":"","mobile":"03-708617","email":"","district":"Baalbeck/Hermil","facebook":"","twitter":"","deputies_terms":"2009","party":"Islamic Action Front","party_ar":"جبهة العمل الإسلامي","sect":"Sunni","born_day":"null","born_month":"null","born_year":"1948","website":"","other_notes":""},{"first_name":"Hussein ","first_name_ar":"حسين","last_name":"Moussawi","last_name_ar":"موسوي","gender":"Male","gender_ar":"ذكر","phone":"","fax":"","mobile":"","email":"","district":"Baalbeck/Hermil","facebook":"","twitter":"","deputies_terms":"2005, 2009","party":"Hezbollah","party_ar":"حزب الله","sect":"Shia","born_day":"null","born_month":"null","born_year":"1943","website":"","other_notes":""},{"first_name":"Hussein ","first_name_ar":"حسين","last_name":"El Hage Hassan","last_name_ar":"الحاج حسن","gender":"Male","gender_ar":"ذكر","phone":"01-271853","fax":"01-271855","mobile":"03-332732","email":"","district":"Baalbeck/Hermil","facebook":"","twitter":"","deputies_terms":"1996, 2000, 2005, 2009","party":"Hezbollah","party_ar":"حزب الله","sect":"Shia","born_day":"null","born_month":"null","born_year":"1960","website":"","other_notes":""},{"first_name":"Nawwar ","first_name_ar":"نوار","last_name":"El Sahili","last_name_ar":"الساحلي","gender":"Male","gender_ar":"ذكر","phone":"01-982100","fax":"","mobile":"03-645222","email":"","district":"Baalbeck/Hermil","facebook":"","twitter":"","deputies_terms":"2005, 2009","party":"Hezbollah","party_ar":"حزب الله","sect":"Shia","born_day":"null","born_month":"null","born_year":"1967","website":"","other_notes":""},{"first_name":"Ali ","first_name_ar":"علي","last_name":"Mekdad","last_name_ar":"مقداد","gender":"Male","gender_ar":"ذكر","phone":"01-982100","fax":"","mobile":"03-666661","email":"","district":"Baalbeck/Hermil","facebook":"","twitter":"","deputies_terms":"2005, 2009","party":"Hezbollah","party_ar":"حزب الله","sect":"Shia","born_day":"null","born_month":"null","born_year":"1961","website":"","other_notes":""},{"first_name":"Ghazi ","first_name_ar":"غازي","last_name":"Zaiter","last_name_ar":"زعيتر","gender":"Male","gender_ar":"ذكر","phone":"01-864364/01-373131","fax":"01-869006","mobile":"03-746764/03-746764","email":"","district":"Baalbeck/Hermil","facebook":"","twitter":"","deputies_terms":"1996, 2000, 2005, 2009","party":"Amal Movement","party_ar":"حركة أمل","sect":"Shia","born_day":"30","born_month":"6","born_year":"1949","website":"","other_notes":""},{"first_name":"Assem ","first_name_ar":"عاصم","last_name":"Qanso","last_name_ar":"قانصو","gender":"Male","gender_ar":"ذكر","phone":"08-225400/01-865311","fax":"","mobile":"03-632422","email":"","district":"Baalbeck/Hermil","facebook":"","twitter":"","deputies_terms":"1996, 2000, 2009","party":"Arab Socialist Ba'ath Party of Lebanon","party_ar":"حزب البعث العربي الاشتراكي في لبنان","sect":"Shia","born_day":"null","born_month":"null","born_year":"1937","website":"","other_notes":""},{"first_name":"Emile ","first_name_ar":"إميل","last_name":"Rahme","last_name_ar":"رحمة","gender":"Male","gender_ar":"ذكر","phone":"","fax":"","mobile":"03-301651","email":"","district":"Baalbeck/Hermil","facebook":"https://www.facebook.com/pages/Emile-Rahme-Official/232446230135821","twitter":"","deputies_terms":"2009","party":"Solidarity Party","party_ar":"حزب التضامن اللبناني","sect":"Maronite","born_day":"null","born_month":"null","born_year":"1952","website":"","other_notes":""},{"first_name":"Marwan ","first_name_ar":"مروان","last_name":"Fares","last_name_ar":"فارس","gender":"Male","gender_ar":"ذكر","phone":"01-868600","fax":"","mobile":"03 321694","email":"","district":"Baalbeck/Hermil","facebook":"","twitter":"","deputies_terms":"1992, 1996, 2000, 2005, 2009","party":"Syrian Social Nationalist Party","party_ar":"الحزب السوري القومي الاجتماعي","sect":"Greek Catholic","born_day":"null","born_month":"null","born_year":"1947","website":"","other_notes":""},{"first_name":"Ali","first_name_ar":"علي","last_name":"Ammar","last_name_ar":"عمار","gender":"Male","gender_ar":"ذكر","phone":"01-450000 - 01-450450","fax":"","mobile":"03-825725","email":"","district":"Baabda","facebook":"","twitter":"","deputies_terms":"1992, 2005, 2009","party":"Hezbollah","party_ar":"حزب الله","sect":"Shia","born_day":"25","born_month":"7","born_year":"1956","website":"","other_notes":""},{"first_name":"Bilal","first_name_ar":"بلال","last_name":"Farhat","last_name_ar":"فرحات","gender":"Male","gender_ar":"ذكر","phone":"","fax":"","mobile":"03-355600","email":"","district":"Baabda","facebook":"","twitter":"","deputies_terms":"2009","party":"Hezbollah","party_ar":"حزب الله","sect":"Shia","born_day":"null","born_month":"null","born_year":"1970","website":"","other_notes":""},{"first_name":"Naji","first_name_ar":"ناجي","last_name":"Gharios","last_name_ar":"غاريوس","gender":"Male","gender_ar":"ذكر","phone":"","fax":"","mobile":"03-440777","email":"","district":"Baabda","facebook":"","twitter":"","deputies_terms":"2009","party":"Free Patriotic Movement","party_ar":"التيار الوطني الحر","sect":"Maronite","born_day":"null","born_month":"null","born_year":"1942","website":"","other_notes":""},{"first_name":"Hikmat","first_name_ar":"حكمت","last_name":"Dib","last_name_ar":"ديب","gender":"Male","gender_ar":"ذكر","phone":"","fax":"","mobile":"03-300678","email":"","district":"Baabda","facebook":"https://www.facebook.com/mphikmatdib","twitter":"","deputies_terms":"2009","party":"Free Patriotic Movement","party_ar":"التيار الوطني الحر","sect":"Maronite","born_day":"16","born_month":"4","born_year":"1956","website":"http://www.hikmatdib.com/","other_notes":""},{"first_name":"Alain","first_name_ar":"آلان","last_name":"Aoun","last_name_ar":"عون","gender":"Male","gender_ar":"ذكر","phone":"","fax":"","mobile":"03-245111","email":"","district":"Baabda","facebook":"https://www.facebook.com/MPAlainAoun","twitter":"https://twitter.com/Alain_Aoun","deputies_terms":"2009","party":"Free Patriotic Movement","party_ar":"التيار الوطني الحر","sect":"Maronite","born_day":"null","born_month":"null","born_year":"1972","website":"","other_notes":""},{"first_name":"Fady","first_name_ar":"فادي","last_name":"El Aawar","last_name_ar":"الأعور","gender":"Male","gender_ar":"ذكر","phone":"","fax":"","mobile":"03-610202","email":"","district":"Baabda","facebook":"","twitter":"","deputies_terms":"2009","party":"Lebanese Democratic Party","party_ar":"الحزب الديمقراطي اللبناني","sect":"Druze","born_day":"25","born_month":"8","born_year":"1960","website":"","other_notes":""},{"first_name":"Henri","first_name_ar":"هنري","last_name":"Helou","last_name_ar":"حلو","gender":"Male","gender_ar":"ذكر","phone":"","fax":"","mobile":"03-277190","email":"","district":"Aley","facebook":"","twitter":"","deputies_terms":"2005, 2009","party":"Progressive Socialist Party","party_ar":"الحزب التقدمي الاشتراكي","sect":"Maronite","born_day":"null","born_month":"null","born_year":"1938","website":"http://www.henrihelou.com/","other_notes":""},{"first_name":"Fouad","first_name_ar":"فؤاد","last_name":"AlSaad","last_name_ar":"السعد","gender":"Male","gender_ar":"ذكر","phone":"","fax":"","mobile":"03-656002","email":"","district":"Aley","facebook":"","twitter":"","deputies_terms":"1992, 2000, 2009","party":"Progressive Socialist Party","party_ar":"الحزب التقدمي الاشتراكي","sect":"Maronite","born_day":"3","born_month":"4","born_year":"1941","website":"","other_notes":""},{"first_name":"Fady","first_name_ar":"فادي","last_name":"Habr","last_name_ar":"الهبر","gender":"Male","gender_ar":"ذكر","phone":"","fax":"","mobile":"","email":"","district":"Aley","facebook":"","twitter":"","deputies_terms":"2009","party":"Kataeb","party_ar":"حزب الكتائب اللبنانية","sect":"Greek Orthodox","born_day":"4","born_month":"1","born_year":"1954","website":"","other_notes":""},{"first_name":"Talal","first_name_ar":"طلال","last_name":"Arslan","last_name_ar":"أرسلان","gender":"Male","gender_ar":"ذكر","phone":"05-802802","fax":"05-434303","mobile":"03-433303","email":"","district":"Aley","facebook":"https://www.facebook.com/talalarslanofficial","twitter":"https://twitter.com/PrinceTalal2013","deputies_terms":"1992, 1996, 2000, 2009","party":"Lebanese Democratic Party","party_ar":"الحزب الديمقراطي اللبناني","sect":"Druze","born_day":"12","born_month":"6","born_year":"1965","website":"http://www.ldparty.org/","other_notes":""},{"first_name":"Akram","first_name_ar":"أكرم","last_name":"Chehayeb","last_name_ar":"شهيب","gender":"Male","gender_ar":"ذكر","phone":"01-308444/05-556600/05-557600","fax":"","mobile":"03-695552/03-388999","email":"","district":"Aley","facebook":"","twitter":"","deputies_terms":"1992, 1996, 2000, 2005, 2009","party":"Progressive Socialist Party","party_ar":"الحزب التقدمي الاشتراكي","sect":"Druze","born_day":"17","born_month":"10","born_year":"1947","website":"","other_notes":""},{"first_name":"Khaled","first_name_ar":"خالد","last_name":"Zahramam","last_name_ar":"زهرمان","gender":"Male","gender_ar":"ذكر","phone":"","fax":"","mobile":"03-003276","email":"","district":"Akkar","facebook":"https://www.facebook.com/pages/النائب-الدكتور-خالد-زهرمان/621371327926332","twitter":"","deputies_terms":"2009","party":"Future Movement","party_ar":"تيار المستقبل","sect":"Sunni","born_day":"6","born_month":"8","born_year":"1966","website":"","other_notes":""},{"first_name":"Khaled","first_name_ar":"خالد","last_name":"El Daher","last_name_ar":"الضاهر","gender":"Male","gender_ar":"ذكر","phone":"","fax":"","mobile":"","email":"","district":"Akkar","facebook":"https://www.facebook.com/Kollona.khaled.el.daher","twitter":"","deputies_terms":"1996, 2009","party":"Future Movement","party_ar":"تيار المستقبل","sect":"Sunni","born_day":"1","born_month":"6","born_year":"1958","website":"","other_notes":""},{"first_name":"Mouiine","first_name_ar":"معين","last_name":"El Merehbi","last_name_ar":"المرعبي","gender":"Male","gender_ar":"ذكر","phone":"","fax":"","mobile":"","email":"","district":"Akkar","facebook":"","twitter":"","deputies_terms":"2009","party":"Future Movement","party_ar":"تيار المستقبل","sect":"Sunni","born_day":"null","born_month":"null","born_year":"1959","website":"","other_notes":""},{"first_name":"Hadi","first_name_ar":"هادي","last_name":"Hobeiche","last_name_ar":"حبيش","gender":"Male","gender_ar":"ذكر","phone":"","fax":"","mobile":"03-216616","email":"","district":"Akkar","facebook":"https://www.facebook.com/Hadyhobeiche","twitter":"https://twitter.com/hadyhobeiche","deputies_terms":"2005, 2009","party":"Future Movement","party_ar":"تيار المستقبل","sect":"Maronite","born_day":"1","born_month":"7","born_year":"1976","website":"","other_notes":""},{"first_name":"Riad","first_name_ar":"رياض","last_name":"Rahal","last_name_ar":"رحال","gender":"Male","gender_ar":"ذكر","phone":"01-982100","fax":"","mobile":"03-645601","email":"","district":"Akkar","facebook":"","twitter":"","deputies_terms":"1996, 2000, 2005, 2009","party":"Future Movement","party_ar":"تيار المستقبل","sect":"Greek Orthodox","born_day":"1","born_month":"5","born_year":"1950","website":"","other_notes":""},{"first_name":"Nidal","first_name_ar":"نضال","last_name":"Tohme","last_name_ar":"طعمه","gender":"Male","gender_ar":"ذكر","phone":"","fax":"","mobile":"03-828131","email":"","district":"Akkar","facebook":"","twitter":"","deputies_terms":"2009","party":"Future Movement","party_ar":"تيار المستقبل","sect":"Greek Orthodox","born_day":"21","born_month":"10","born_year":"1960","website":"","other_notes":""},{"first_name":"Khodr","first_name_ar":"خضر","last_name":"Habib","last_name_ar":"حبيب","gender":"Male","gender_ar":"ذكر","phone":"","fax":"","mobile":"03-749100","email":"","district":"Akkar","facebook":"","twitter":"","deputies_terms":"2009","party":"Future Movement","party_ar":"تيار المستقبل","sect":"Alawite","born_day":"null","born_month":"null","born_year":"1962","website":"http://khodorhabib.com/online/index.php","other_notes":""},{"first_name":"Bahia","first_name_ar":"بهية","last_name":"Hariri","last_name_ar":"الحريري","gender":"Female","gender_ar":"أنثى","phone":"07-723221","fax":"07-724740","mobile":"03-720000 (TBC)","email":"","district":"Saida","facebook":"","twitter":"https://twitter.com/BahiaHariri","deputies_terms":"2009","party":"Future Movement","party_ar":"تيار المستقبل","sect":"Sunni","born_day":"null","born_month":"null","born_year":"1953","website":"","other_notes":""},{"first_name":"Gilberte","first_name_ar":"جلبيرت","last_name":"Zouein","last_name_ar":"زوين","gender":"Female","gender_ar":"أنثى","phone":"01-982100","fax":"","mobile":"03-634142","email":"","district":"Kesserwan","facebook":"","twitter":"","deputies_terms":"2005, 2009","party":"Free Patriotic Movement","party_ar":"التيار الوطني الحر","sect":"Maronite","born_day":"null","born_month":"null","born_year":"1952","website":"","other_notes":""},{"first_name":"Strida","first_name_ar":"ستريدا","last_name":"Geagea","last_name_ar":"جعجع","gender":"Female","gender_ar":"أنثى","phone":"01-982100","fax":"","mobile":"","email":"","district":"Bsharri","facebook":"https://www.facebook.com/sthridageagea","twitter":"","deputies_terms":"2005, 2009","party":"Lebanese Forces","party_ar":"القوات اللبنانية","sect":"Maronite","born_day":"31","born_month":"5","born_year":"1967","website":"","other_notes":""},{"first_name":"Nayla ","first_name_ar":"نايلة","last_name":"Tueni","last_name_ar":"تويني","gender":"Female","gender_ar":"أنثى","phone":"01-974418","fax":"01-970375","mobile":"03-340000","email":"nayla.tueni@annahar.com","district":"Beirut I","facebook":"https://www.facebook.com/pages/Nayla-Tueni/12727061862","twitter":"https://twitter.com/naylatueni","deputies_terms":"2009","party":"Independent within 14 March","party_ar":"مستقل مع ١٤ آذار","sect":"Greek Orthodox","born_day":"31","born_month":"8","born_year":"1982","website":"","other_notes":""},{"first_name":"Kathem","first_name_ar":"كاظم","last_name":"El Kheir","last_name_ar":"الخير","gender":"Male","gender_ar":"ذكر","phone":"","fax":"","mobile":"","email":"","district":"Dinniyeh & Minieh","facebook":"https://www.facebook.com/pages/Kazem-saleh-el-kheir/442232445838106","twitter":"https://twitter.com/kazemkheir","deputies_terms":"2009","party":"Tripoli Bloc","party_ar":"التكتل الطرابلسي","sect":"Sunni","born_day":"null","born_month":"null","born_year":"1982","website":"","other_notes":""}]